yaml_settings_pydantic/__init__.py
yaml_settings_pydantic/__main__.py
yaml_settings_pydantic/py.typed
yaml_settings_pydantic-2.3.2.dist-info/LICENSE
yaml_settings_pydantic-2.3.2.dist-info/METADATA
yaml_settings_pydantic-2.3.2.dist-info/WHEEL
yaml_settings_pydantic-2.3.2.dist-info/RECORD
