Metadata-Version: 2.1
Name: yaml-settings-pydantic
Version: 2.3.2
Summary: A tool to easily load (many) JSON/YAML files as pydantic settings.
License: MIT
Keywords: env,config,pydantic,settings,pydantic-settings,yaml,json,yaml-settings-pydantic
Author: Adrian Cederberg
Author-email: adrn.cederberg123@gmail.com
Maintainer: Adrian Cederberg
Maintainer-email: adrn.cederberg123@gmail.com
Requires-Python: >=3.9,<4.0
Classifier: Development Status :: 5 - Production/Stable
Classifier: Environment :: Console
Classifier: Environment :: MacOS X
Classifier: Framework :: Hypothesis
Classifier: Intended Audience :: Developers
Classifier: Intended Audience :: Information Technology
Classifier: Intended Audience :: System Administrators
Classifier: License :: OSI Approved :: MIT License
Classifier: Operating System :: POSIX :: Linux
Classifier: Operating System :: Unix
Classifier: Programming Language :: Python
Classifier: Programming Language :: Python :: 3
Classifier: Programming Language :: Python :: 3.9
Classifier: Programming Language :: Python :: 3.10
Classifier: Programming Language :: Python :: 3.11
Classifier: Programming Language :: Python :: 3.12
Classifier: Programming Language :: Python :: 3 :: Only
Classifier: Topic :: Internet
Classifier: Topic :: Software Development :: Libraries :: Python Modules
Classifier: Typing :: Typed
Requires-Dist: jsonpath-ng (>=1.6.1,<2.0.0)
Requires-Dist: pydantic (>=2.8.0,<3.0.0)
Requires-Dist: pydantic-settings (>=2.3.4,<3.0.0)
Requires-Dist: pyyaml (>=6.0.1,<7.0.0)
